vibeiseven/__init__.py
vibeiseven/example.py
vibeiseven-1.0.0.dist-info/licenses/LICENSE
vibeiseven-1.0.0.dist-info/METADATA
vibeiseven-1.0.0.dist-info/WHEEL
vibeiseven-1.0.0.dist-info/top_level.txt
vibeiseven-1.0.0.dist-info/RECORD
