Metadata-Version: 2.4
Name: vibeiseven
Version: 1.0.0
Summary: AI-powered even number detection using GPT or Gemini
Author: Dean Billedo
Author-email: Dean BIlledo <deanreight@gmail.com>
License: MIT License
Classifier: Programming Language :: Python :: 3.7
Classifier: License :: OSI Approved :: MIT License
Classifier: Intended Audience :: Developers
Classifier: Topic :: Scientific/Engineering :: Artificial Intelligence
Requires-Python: >=3.7
License-File: LICENSE
Requires-Dist: openai>=1.0.0
Requires-Dist: google-generativeai
Dynamic: author
Dynamic: license-file
Dynamic: requires-python
